{"hours":[{"temp":1.7,"precipitation":0,"weathercode":0,"cloudcover":3,"condition":"cold","multiplier":1.1},{"temp":1.7,"precipitation":0,"weathercode":0,"cloudcover":0,"condition":"cold","multiplier":1.1},{"temp":1.7,"precipitation":0,"weathercode":0,"cloudcover":0,"condition":"cold","multiplier":1.1},{"temp":1.8,"precipitation":0,"weathercode":0,"cloudcover":0,"condition":"cold","multiplier":1.1},{"temp":1.9,"precipitation":0,"weathercode":0,"cloudcover":0,"condition":"cold","multiplier":1.1},{"temp":2.1,"precipitation":0,"weathercode":0,"cloudcover":0,"condition":"cold","multiplier":1.1},{"temp":2.7,"precipitation":0,"weathercode":0,"cloudcover":0,"condition":"cold","multiplier":1.1},{"temp":2.7,"precipitation":0,"weathercode":0,"cloudcover":0,"condition":"cold","multiplier":1.1},{"temp":2.9,"precipitation":0,"weathercode":0,"cloudcover":0,"condition":"cold","multiplier":1.1},{"temp":3.3,"precipitation":0,"weathercode":0,"cloudcover":16,"condition":"cold","multiplier":1.1},{"temp":4.2,"precipitation":0,"weathercode":0,"cloudcover":17,"condition":"cold","multiplier":1.1},{"temp":5.4,"precipitation":0,"weathercode":1,"cloudcover":20,"condition":"default","multiplier":1},{"temp":6.2,"precipitation":0,"weathercode":0,"cloudcover":0,"condition":"default","multiplier":1},{"temp":6.7,"precipitation":0,"weathercode":0,"cloudcover":0,"condition":"default","multiplier":1},{"temp":7,"precipitation":0,"weathercode":0,"cloudcover":0,"condition":"default","multiplier":1},{"temp":6.8,"precipitation":0,"weathercode":0,"cloudcover":0,"condition":"default","multiplier":1},{"temp":6.1,"precipitation":0,"weathercode":0,"cloudcover":0,"condition":"default","multiplier":1},{"temp":5.5,"precipitation":0,"weathercode":0,"cloudcover":0,"condition":"default","multiplier":1},{"temp":4.2,"precipitation":0,"weathercode":0,"cloudcover":5,"condition":"cold","multiplier":1.1},{"temp":3.9,"precipitation":0,"weathercode":0,"cloudcover":12,"condition":"cold","multiplier":1.1},{"temp":3.6,"precipitation":0,"weathercode":3,"cloudcover":100,"condition":"cold","multiplier":1.1},{"temp":3,"precipitation":0,"weathercode":45,"cloudcover":100,"condition":"cold","multiplier":1.1},{"temp":3.2,"precipitation":0,"weathercode":0,"cloudcover":6,"condition":"cold","multiplier":1.1},{"temp":3.3,"precipitation":0,"weathercode":0,"cloudcover":2,"condition":"cold","multiplier":1.1}],"summary":{"avgTemp":3.8,"avgMultiplier":1.07,"hasRain":false}}